fairops/__init__.py
fairops/cli.py
fairops/version.py
fairops/clitools/configure_cli.py
fairops/clitools/docker_cli.py
fairops/clitools/helpers.py
fairops/clitools/mlops_cli.py
fairops/devops/__init__.py
fairops/devops/container.py
fairops/mlops/__init__.py
fairops/mlops/autolog.py
fairops/mlops/helpers.py
fairops/mlops/models.py
fairops/repositories/__init__.py
fairops/repositories/figshare.py
fairops/repositories/zenodo.py
fairops/utils/__init__.py
fairops/utils/decorators.py
fairops/utils/envpath.py
fairops-0.2.7.dist-info/licenses/LICENSE
fairops-0.2.7.dist-info/METADATA
fairops-0.2.7.dist-info/WHEEL
fairops-0.2.7.dist-info/entry_points.txt
fairops-0.2.7.dist-info/top_level.txt
fairops-0.2.7.dist-info/RECORD
