Metadata-Version: 2.4
Name: fairops
Version: 0.2.7
Summary: A Python library for FAIR AI/ML ops pipelines
Author-email: Wade Schulz <wade.schulz@yale.edu>
License: MIT
Project-URL: Homepage, https://github.com/acomphealth/fairops
Requires-Python: >=3.10
License-File: LICENSE
Requires-Dist: requests<3.0.0,>=2.32.3
Requires-Dist: tqdm<5.0.0,>=4.67.1
Requires-Dist: pandas<3.0.0,>=2.2.3
Requires-Dist: docker<8.0.0,>=7.1.0
Requires-Dist: click<9.0.0,>=8.0.0
Requires-Dist: questionary<3.0.0,>=2.1.0
Requires-Dist: rocrate<1.0.0,>=0.13.0
Dynamic: license-file
